odoo/addons/purchase_stock_picking_show_currency_rate/README.rst
odoo/addons/purchase_stock_picking_show_currency_rate/__init__.py
odoo/addons/purchase_stock_picking_show_currency_rate/__manifest__.py
odoo/addons/purchase_stock_picking_show_currency_rate/i18n/es.po
odoo/addons/purchase_stock_picking_show_currency_rate/i18n/purchase_stock_picking_show_currency_rate.pot
odoo/addons/purchase_stock_picking_show_currency_rate/models/__init__.py
odoo/addons/purchase_stock_picking_show_currency_rate/models/stock_picking.py
odoo/addons/purchase_stock_picking_show_currency_rate/readme/CONFIGURE.rst
odoo/addons/purchase_stock_picking_show_currency_rate/readme/CONTRIBUTORS.rst
odoo/addons/purchase_stock_picking_show_currency_rate/readme/DESCRIPTION.rst
odoo/addons/purchase_stock_picking_show_currency_rate/readme/USAGE.rst
odoo/addons/purchase_stock_picking_show_currency_rate/static/description/icon.png
odoo/addons/purchase_stock_picking_show_currency_rate/static/description/index.html
odoo/addons/purchase_stock_picking_show_currency_rate/tests/__init__.py
odoo/addons/purchase_stock_picking_show_currency_rate/tests/test_purchase_stock_picking.py
odoo/addons/purchase_stock_picking_show_currency_rate/views/stock_picking_view.xml
odoo13_addon_purchase_stock_picking_show_currency_rate-13.0.1.0.1.dist-info/METADATA
odoo13_addon_purchase_stock_picking_show_currency_rate-13.0.1.0.1.dist-info/WHEEL
odoo13_addon_purchase_stock_picking_show_currency_rate-13.0.1.0.1.dist-info/top_level.txt
odoo13_addon_purchase_stock_picking_show_currency_rate-13.0.1.0.1.dist-info/RECORD
